PE.v
module PE (
    input               clk,
    input               rst_n,
    input               en,
    input  [7:0]        A_in,
    input  [7:0]        B_in,
    
    output reg          done,
    output reg          start,
    output reg [7:0]    A_out,
    output reg [7:0]    B_out,
    output reg [15:0]   C_out
);

    parameter IDLE    = 2'b00;
    parameter READ    = 2'b01;
    parameter COMPUTE = 2'b10;
    parameter DONE    = 2'b11;

    reg [1:0] CurrentState, NextState;
    reg [7:0] A_reg, B_reg;
    reg [15:0]  product;
    reg [15:0]  accumulate;
    reg finish;

    // State Transition
    always @(posedge clk) begin
        if (!rst_n) begin
            CurrentState <= IDLE;
        end else begin
            CurrentState <= NextState;
        end
    end

    // State Logic
    always @(*) begin
        case (CurrentState)
            IDLE:
                if (en) begin
                    NextState <= READ;
                end else begin
                    NextState = IDLE;
                end

            READ:
                NextState = COMPUTE;

            COMPUTE:
                if (finish) begin
                    NextState = DONE;
                end else begin
                    NextState = COMPUTE;    
                end

            DONE:
                     NextState = IDLE;

            default:
                NextState = IDLE;
        endcase
    end

    // Output and Register Logic
    always @(posedge clk) begin
        if (!rst_n) begin
            product <= 0;
            accumulate <= 0;
            A_out <= 0;
            B_out <= 0;
            C_out <= 0;
            start <= 0;
            done <= 0;
            finish <= 0;
        end else begin
            case (CurrentState)
                IDLE: begin
                    start <= 1;
                    done <= 0;
                    finish <= 0; // Reset for next operation
                end

                READ: begin
                    start <= 0;
                    A_reg <= A_in;
                    B_reg <= B_in;
                end

                COMPUTE: begin
                    if(!finish) begin
                    product <= (A_reg * B_reg);
                    accumulate <= accumulate + product;
                    finish <= 1;
                    end
                    
                end

                DONE: begin
                    A_out <= A_reg;
                    B_out <= B_reg;
                    C_out <= accumulate;
                    done <= 1;
                    finish <= 0;  // Reset finish
                end

                default: begin
                    product <= 0;
                    accumulate <= 0;
                end
            endcase
        end
    end

endmodule

/*
    always @(posedge clk ) begin
        if (!rst_n) begin
          //  A_reg <= 0;
          //  B_reg <= 0;
            product <= 0;
            accumulate   <= 0;
            A_out <= 0;
            B_out <= 0;
            C_out <= 0;
            start <= 0;
            done  <= 0;
           

        end else if (en) begin
        
            //A_reg <= A_in;
            //B_reg <= B_in;

            // Multiply and accumulate
            start <= 1;
            product <=  (A_in * B_in);
            accumulate <= accumulate + product;
            
            
            // Pass registered A and B to next PE
            A_out <= A_in;
            B_out <= B_in;

            // Output accumulated result
            C_out <= accumulate;
            start <=0;
        end
    end
*/

tb_PE.v
`timescale 1ns / 1ps

module PE_tb;

    reg clk;
    reg rst_n;
    reg en;
    reg [7:0] A_in, B_in;
    
    wire done, start;
    wire [7:0] A_out, B_out;
    wire [15:0] C_out;
    
    // Instantiate PE module
    PE uut (
        .clk(clk),
        .rst_n(rst_n),
        .en(en),
        .A_in(A_in),
        .B_in(B_in),
        .done(done),
        .start(start),
        .A_out(A_out),
        .B_out(B_out),
        .C_out(C_out)
    );

    // Clock generation (50MHz)
    always #10 clk = ~clk;  // 20ns period

    // Stimulus
    initial begin
        $dumpfile("PE_tb.vcd");
        $dumpvars(0, PE_tb);

        clk = 0;
        rst_n = 0;
        en = 0;
        A_in = 0;
        B_in = 0;

        #20;
        rst_n = 1;
        #10;

         
        en = 1;
        A_in = 8'd5;
        B_in = 8'd8;
        #20;  
        wait(done); 

        #10;         

        
        A_in = 8'd2;
        B_in = 8'd5;
        #20;
        wait(done);
        #10;

        A_in = 8'd255;
        B_in = 8'd255;
        #20;
        wait(done);
        #10;
        A_in = 8'd8;
        B_in = 8'd7;
        #20;
        wait(done);
        #10;
        A_in = 8'd4;
        B_in = 8'd5;
        #20;
        wait(done);
        #10;
        A_in = 8'd29;
        B_in = 8'd121;
        #20;
        wait(done);
        #10;
        A_in = 8'd69;
        B_in = 8'd16;
        #20;
        wait(done);
        #10;
        A_in = 8'd120;
        B_in = 8'd255;
        #20;
        wait(done);
        #10;
        A_in = 8'd147;
        B_in = 8'd51;
        #20;
        wait(done);
        #10;
        A_in = 8'd120;
        B_in = 8'd129;
        #20;
        wait(done);
        #10;
        A_in = 8'd221;
        B_in = 8'd237;
        #20;
        wait(done);
        #10;

       
        // Final wait
        #100;
        en =0;
        $finish;
    end

endmodule

PE_tb.vcd
$date
	Wed Mar 26 09:06:50 2025
$end
$version
	Icarus Verilog
$end
$timescale
	1ps
$end
$scope module PE_tb $end
$var wire 1 ! start $end
$var wire 1 " done $end
$var wire 16 # C_out [15:0] $end
$var wire 8 $ B_out [7:0] $end
$var wire 8 % A_out [7:0] $end
$var reg 8 & A_in [7:0] $end
$var reg 8 ' B_in [7:0] $end
$var reg 1 ( clk $end
$var reg 1 ) en $end
$var reg 1 * rst_n $end
$scope module uut $end
$var wire 8 + A_in [7:0] $end
$var wire 8 , B_in [7:0] $end
$var wire 1 ( clk $end
$var wire 1 ) en $end
$var wire 1 * rst_n $end
$var parameter 2 - COMPUTE $end
$var parameter 2 . DONE $end
$var parameter 2 / IDLE $end
$var parameter 2 0 READ $end
$var reg 8 1 A_out [7:0] $end
$var reg 8 2 A_reg [7:0] $end
$var reg 8 3 B_out [7:0] $end
$var reg 8 4 B_reg [7:0] $end
$var reg 16 5 C_out [15:0] $end
$var reg 2 6 CurrentState [1:0] $end
$var reg 2 7 NextState [1:0] $end
$var reg 16 8 accumulate [15:0] $end
$var reg 1 " done $end
$var reg 1 9 finish $end
$var reg 16 : product [15:0] $end
$var reg 1 ! start $end
$upscope $end
$upscope $end
$enddefinitions $end
$comment Show the parameter values. $end
$dumpall
b1 0
b0 /
b11 .
b10 -
$end
#0
$dumpvars
bx :
x9
bx 8
b0 7
bx 6
bx 5
bx 4
bx 3
bx 2
bx 1
b0 ,
b0 +
0*
0)
0(
b0 '
b0 &
bx %
bx $
bx #
x"
x!
$end
#10000
b0 6
09
0"
0!
b0 #
b0 5
b0 $
b0 3
b0 %
b0 1
b0 8
b0 :
1(
#20000
0(
1*
#30000
1!
b1 7
1(
b1000 '
b1000 ,
b101 &
b101 +
1)
#40000
0(
#50000
b10 7
b1 6
1(
#60000
0(
#70000
b1000 4
b101 2
0!
b10 6
1(
#80000
0(
#90000
b11 7
19
b101000 :
1(
#100000
0(
#110000
b0 7
b11 6
1(
#120000
0(
#130000
b1 7
b0 6
09
1"
b1000 $
b1000 3
b101 %
b101 1
1(
#140000
b101 '
b101 ,
b10 &
b10 +
0(
#150000
b10 7
0"
1!
b1 6
1(
#160000
0(
#170000
b10 6
b101 4
b10 2
0!
1(
#180000
0(
#190000
b11 7
19
b101000 8
b1010 :
1(
#200000
0(
#210000
b0 7
b11 6
1(
#220000
0(
#230000
b1 7
09
1"
b101000 #
b101000 5
b101 $
b101 3
b10 %
b10 1
b0 6
1(
#240000
b11111111 '
b11111111 ,
b11111111 &
b11111111 +
0(
#250000
b10 7
b1 6
0"
1!
1(
#260000
0(
#270000
b11111111 4
b11111111 2
0!
b10 6
1(
#280000
0(
#290000
b11 7
19
b110010 8
b1111111000000001 :
1(
#300000
0(
#310000
b0 7
b11 6
1(
#320000
0(
#330000
b1 7
b0 6
09
1"
b110010 #
b110010 5
b11111111 $
b11111111 3
b11111111 %
b11111111 1
1(
#340000
b111 '
b111 ,
b1000 &
b1000 +
0(
#350000
b10 7
0"
1!
b1 6
1(
#360000
0(
#370000
b10 6
b111 4
b1000 2
0!
1(
#380000
0(
#390000
b11 7
19
b1111111000110011 8
b111000 :
1(
#400000
0(
#410000
b0 7
b11 6
1(
#420000
0(
#430000
b1 7
09
1"
b1111111000110011 #
b1111111000110011 5
b111 $
b111 3
b1000 %
b1000 1
b0 6
1(
#440000
b101 '
b101 ,
b100 &
b100 +
0(
#450000
b10 7
b1 6
0"
1!
1(
#460000
0(
#470000
b101 4
b100 2
0!
b10 6
1(
#480000
0(
#490000
b11 7
19
b1111111001101011 8
b10100 :
1(
#500000
0(
#510000
b0 7
b11 6
1(
#520000
0(
#530000
b1 7
b0 6
09
1"
b1111111001101011 #
b1111111001101011 5
b101 $
b101 3
b100 %
b100 1
1(
#540000
b1111001 '
b1111001 ,
b11101 &
b11101 +
0(
#550000
b10 7
0"
1!
b1 6
1(
#560000
0(
#570000
b10 6
b1111001 4
b11101 2
0!
1(
#580000
0(
#590000
b11 7
19
b1111111001111111 8
b110110110101 :
1(
#600000
0(
#610000
b0 7
b11 6
1(
#620000
0(
#630000
b1 7
09
1"
b1111111001111111 #
b1111111001111111 5
b1111001 $
b1111001 3
b11101 %
b11101 1
b0 6
1(
#640000
b10000 '
b10000 ,
b1000101 &
b1000101 +
0(
#650000
b10 7
b1 6
0"
1!
1(
#660000
0(
#670000
b10000 4
b1000101 2
0!
b10 6
1(
#680000
0(
#690000
b11 7
19
b110000110100 8
b10001010000 :
1(
#700000
0(
#710000
b0 7
b11 6
1(
#720000
0(
#730000
b1 7
b0 6
09
1"
b110000110100 #
b110000110100 5
b10000 $
b10000 3
b1000101 %
b1000101 1
1(
#740000
b11111111 '
b11111111 ,
b1111000 &
b1111000 +
0(
#750000
b10 7
0"
1!
b1 6
1(
#760000
0(
#770000
b10 6
b11111111 4
b1111000 2
0!
1(
#780000
0(
#790000
b11 7
19
b1000010000100 8
b111011110001000 :
1(
#800000
0(
#810000
b0 7
b11 6
1(
#820000
0(
#830000
b1 7
09
1"
b1000010000100 #
b1000010000100 5
b11111111 $
b11111111 3
b1111000 %
b1111000 1
b0 6
1(
#840000
b110011 '
b110011 ,
b10010011 &
b10010011 +
0(
#850000
b10 7
b1 6
0"
1!
1(
#860000
0(
#870000
b110011 4
b10010011 2
0!
b10 6
1(
#880000
0(
#890000
b11 7
19
b1000100000001100 8
b1110101001001 :
1(
#900000
0(
#910000
b0 7
b11 6
1(
#920000
0(
#930000
b1 7
b0 6
09
1"
b1000100000001100 #
b1000100000001100 5
b110011 $
b110011 3
b10010011 %
b10010011 1
1(
#940000
b10000001 '
b10000001 ,
b1111000 &
b1111000 +
0(
#950000
b10 7
0"
1!
b1 6
1(
#960000
0(
#970000
b10 6
b10000001 4
b1111000 2
0!
1(
#980000
0(
#990000
b11 7
19
b1010010101010101 8
b11110001111000 :
1(
#1000000
0(
#1010000
b0 7
b11 6
1(
#1020000
0(
#1030000
b1 7
09
1"
b1010010101010101 #
b1010010101010101 5
b10000001 $
b10000001 3
b1111000 %
b1111000 1
b0 6
1(
#1040000
b11101101 '
b11101101 ,
b11011101 &
b11011101 +
0(
#1050000
b10 7
b1 6
0"
1!
1(
#1060000
0(
#1070000
b11101101 4
b11011101 2
0!
b10 6
1(
#1080000
0(
#1090000
b11 7
19
b1110000111001101 8
b1100110010011001 :
1(
#1100000
0(
#1110000
b0 7
b11 6
1(
#1120000
0(
#1130000
b1 7
b0 6
09
1"
b1110000111001101 #
b1110000111001101 5
b11101101 $
b11101101 3
b11011101 %
b11011101 1
1(
#1140000
0(
#1150000
b10 7
0"
1!
b1 6
1(
#1160000
0(
#1170000
b10 6
0!
1(
#1180000
0(
#1190000
b11 7
19
b1010111001100110 8
1(
#1200000
0(
#1210000
b0 7
b11 6
1(
#1220000
0(
#1230000
b1 7
09
1"
b1010111001100110 #
b1010111001100110 5
b0 6
1(
#1240000
b0 7
0(
0)
