PE.v
module PE (
    input               clk,
    input               rst_n,
    input               en,
    input  [7:0]        A_in,
    input  [7:0]        B_in,
    
   
    output reg [7:0]    A_out,   // Correct: declare as reg because assigned in always block
    output reg [7:0]    B_out,   // Correct: declare as reg because assigned in always block
    output reg [15:0]   C_out    // Correct: declare as reg to hold result
);

    // Internal registers
    reg [7:0]   A_reg;
    reg [7:0]   B_reg;
    reg [15:0]  product;
    reg [15:0]  accumulate;

    always @(posedge clk ) begin
        if (!rst_n) begin
            A_reg <= 0;
            B_reg <= 0;
            product <= 0;
            accumulate   <= 0;
            A_out <= 0;
            B_out <= 0;
            C_out <= 0;
           

        end else if (en) begin
        
            A_reg <= A_in;
            B_reg <= B_in;

            // Multiply and accumulate
            if (A_reg != 0 && B_reg !=0) begin
            product <=  (A_reg * B_reg);
            accumulate <= accumulate + product;
            end else begin
                
                accumulate <= accumulate; 
            
            end
            
            // Pass registered A and B to next PE
            A_out <= A_reg;
            B_out <= B_reg;

            // Output accumulated result
            C_out <= accumulate;
        end
    end

endmodule

tb_PE.v
`timescale 1ns / 1ps

module tb_PE;

    // Parameters
    parameter DATA_WIDTH = 8;
    parameter ACC_WIDTH  = 16;

    // Testbench signals
    reg                   clk;
    reg                   rst_n;
    reg                   en;
    reg  [DATA_WIDTH-1:0] A_in;
    reg  [DATA_WIDTH-1:0] B_in;
    wire [DATA_WIDTH-1:0] A_out;
    wire [DATA_WIDTH-1:0] B_out;
    wire [ACC_WIDTH-1:0]  C_out;

    // Instantiate the PE module
    PE uut (
        .clk(clk),
        .rst_n(rst_n),
        .en(en),
        .A_in(A_in),
        .B_in(B_in),
        .A_out(A_out),
        .B_out(B_out),
        .C_out(C_out)
    );

    // Clock generation (10ns period)
    always #5 clk = ~clk;

    // Test sequence
    initial begin
        // Initialize signals
        clk   = 1;
        rst_n = 0;
        en    = 0;
        A_in  = 0;
        B_in  = 0;

        // Reset pulse
        #10;
        rst_n = 1;

        // Wait a cycle
        #10;

        // Enable PE and apply inputs
        en = 1;

        // Test vector 1
        A_in = 8'd3;  // A = 3
        B_in = 8'd4;  // B = 4
        #10;          // Wait for 1 clock

        // Test vector 2
        A_in = 8'd2;  // A = 2
        B_in = 8'd5;  // B = 5
        #10;          // Wait for 1 clock

        // Test vector 3
        A_in = 8'd0;  // A = 1
        B_in = 8'd6;  // B = 6
        #10;          // Wait for 1 clock

        // Test vector 4
        A_in = 8'd2;  // A = 0 (end of data)
        B_in = 8'd8;  // B = 0
        #50;          // Wait for 1 clock

        // Disable PE
        en = 0;

        // Wait for a few more cycles to observe outputs
       

        // Finish simulation
        #200;
        $finish;
    end

    // Monitor for debug (optional console output)
    initial begin
        $monitor("Time = %0t | A_in = %d, B_in = %d | A_out = %d, B_out = %d | C_out = %d", 
                  $time, A_in, B_in, A_out, B_out, C_out);
    end

    // VCD Dump for waveform viewing
    initial begin
        $dumpfile("tb_PE.vcd");   // Name of VCD file to generate
        $dumpvars(0, tb_PE);     // Dump all variables in this module (recursive)
    end

endmodule

tb_PE.vcd
$date
	Thu Mar 20 20:03:22 2025
$end
$version
	Icarus Verilog
$end
$timescale
	1ps
$end
$scope module tb_PE $end
$var wire 16 ! C_out [15:0] $end
$var wire 8 " B_out [7:0] $end
$var wire 8 # A_out [7:0] $end
$var parameter 32 $ ACC_WIDTH $end
$var parameter 32 % DATA_WIDTH $end
$var reg 8 & A_in [7:0] $end
$var reg 8 ' B_in [7:0] $end
$var reg 1 ( clk $end
$var reg 1 ) en $end
$var reg 1 * rst_n $end
$scope module uut $end
$var wire 8 + A_in [7:0] $end
$var wire 8 , B_in [7:0] $end
$var wire 1 ( clk $end
$var wire 1 ) en $end
$var wire 1 * rst_n $end
$var reg 8 - A_out [7:0] $end
$var reg 8 . A_reg [7:0] $end
$var reg 8 / B_out [7:0] $end
$var reg 8 0 B_reg [7:0] $end
$var reg 16 1 C_out [15:0] $end
$var reg 16 2 accumulate [15:0] $end
$var reg 16 3 product [15:0] $end
$upscope $end
$upscope $end
$enddefinitions $end
$comment Show the parameter values. $end
$dumpall
b1000 %
b10000 $
$end
#0
$dumpvars
b0 3
b0 2
b0 1
b0 0
b0 /
b0 .
b0 -
b0 ,
b0 +
0*
0)
1(
b0 '
b0 &
b0 #
b0 "
b0 !
$end
#5000
0(
#10000
1(
1*
#15000
0(
#20000
b100 0
b11 .
1(
b100 '
b100 ,
b11 &
b11 +
1)
#25000
0(
#30000
b100 "
b100 /
b11 #
b11 -
b1100 3
b101 0
b10 .
1(
b101 '
b101 ,
b10 &
b10 +
#35000
0(
#40000
b101 "
b101 /
b10 #
b10 -
b1100 2
b1010 3
b110 0
b0 .
1(
b110 '
b110 ,
b0 &
b0 +
#45000
0(
#50000
b1100 !
b1100 1
b110 "
b110 /
b0 #
b0 -
b1000 0
b10 .
1(
b1000 '
b1000 ,
b10 &
b10 +
#55000
0(
#60000
b1000 "
b1000 /
b10 #
b10 -
b10110 2
b10000 3
1(
#65000
0(
#70000
b10110 !
b10110 1
b100110 2
1(
#75000
0(
#80000
b100110 !
b100110 1
b110110 2
1(
#85000
0(
#90000
b110110 !
b110110 1
b1000110 2
1(
#95000
0(
#100000
1(
0)
